[
  {
    "date_est": "2025-06-11",
    "event_id": 401695918,
    "player_id": 36969,
    "name": "Juan Soto",
    "team": "Mets",
    "opponent": "Nationals",
    "metric": "r",
    "count": 14,
    "ab": 37,
    "date_range": "15",
    "count_per_ab": 0.378,
    "ab_per_game": 3.364,
    "expected_count_per_game": 1.273
  },
  {
    "date_est": "2025-06-11",
    "event_id": 401695925,
    "player_id": 39572,
    "name": "Luis Arraez",
    "team": "Padres",
    "opponent": "Dodgers",
    "metric": "r",
    "count": 10,
    "ab": 53,
    "date_range": "15",
    "count_per_ab": 0.189,
    "ab_per_game": 4.077,
    "expected_count_per_game": 0.769
  },
  {
    "date_est": "2025-06-11",
    "event_id": 401695920,
    "player_id": 41273,
    "name": "Jeremy Pena",
    "team": "Astros",
    "opponent": "White Sox",
    "metric": "r",
    "count": 10,
    "ab": 50,
    "date_range": "15",
    "count_per_ab": 0.2,
    "ab_per_game": 4.167,
    "expected_count_per_game": 0.833
  },
  {
    "date_est": "2025-06-11",
    "event_id": 401695918,
    "player_id": 37498,
    "name": "Pete Alonso",
    "team": "Mets",
    "opponent": "Nationals",
    "metric": "r",
    "count": 10,
    "ab": 47,
    "date_range": "15",
    "count_per_ab": 0.213,
    "ab_per_game": 4.273,
    "expected_count_per_game": 0.909
  },
  {
    "date_est": "2025-06-11",
    "event_id": 401695925,
    "player_id": 31097,
    "name": "Manny Machado",
    "team": "Padres",
    "opponent": "Dodgers",
    "metric": "r",
    "count": 9,
    "ab": 54,
    "date_range": "15",
    "count_per_ab": 0.167,
    "ab_per_game": 4.154,
    "expected_count_per_game": 0.692
  },
  {
    "date_est": "2025-06-11",
    "event_id": 401695919,
    "player_id": 4917869,
    "name": "Jackson Chourio",
    "team": "Brewers",
    "opponent": "Braves",
    "metric": "r",
    "count": 9,
    "ab": 44,
    "date_range": "15",
    "count_per_ab": 0.205,
    "ab_per_game": 4.4,
    "expected_count_per_game": 0.9
  },
  {
    "date_est": "2025-06-11",
    "event_id": 401695925,
    "player_id": 35983,
    "name": "Fernando Tatis Jr.",
    "team": "Padres",
    "opponent": "Dodgers",
    "metric": "r",
    "count": 9,
    "ab": 44,
    "date_range": "15",
    "count_per_ab": 0.205,
    "ab_per_game": 3.667,
    "expected_count_per_game": 0.75
  },
  {
    "date_est": "2025-06-11",
    "event_id": 401695918,
    "player_id": 32159,
    "name": "Brandon Nimmo",
    "team": "Mets",
    "opponent": "Nationals",
    "metric": "r",
    "count": 9,
    "ab": 42,
    "date_range": "15",
    "count_per_ab": 0.214,
    "ab_per_game": 3.818,
    "expected_count_per_game": 0.818
  },
  {
    "date_est": "2025-06-11",
    "event_id": 401695918,
    "player_id": 32129,
    "name": "Francisco Lindor",
    "team": "Mets",
    "opponent": "Nationals",
    "metric": "r",
    "count": 9,
    "ab": 39,
    "date_range": "15",
    "count_per_ab": 0.231,
    "ab_per_game": 3.9,
    "expected_count_per_game": 0.9
  },
  {
    "date_est": "2025-06-11",
    "event_id": 401695927,
    "player_id": 42404,
    "name": "Corbin Carroll",
    "team": "D-Backs",
    "opponent": "Mariners",
    "metric": "r",
    "count": 9,
    "ab": 38,
    "date_range": "15",
    "count_per_ab": 0.237,
    "ab_per_game": 3.455,
    "expected_count_per_game": 0.818
  },
  {
    "date_est": "2025-06-11",
    "event_id": 401695917,
    "player_id": 33859,
    "name": "Rafael Devers",
    "team": "Red Sox",
    "opponent": "Rays",
    "metric": "r",
    "count": 9,
    "ab": 37,
    "date_range": "15",
    "count_per_ab": 0.243,
    "ab_per_game": 3.7,
    "expected_count_per_game": 0.9
  },
  {
    "date_est": "2025-06-11",
    "event_id": 401695923,
    "player_id": 4683365,
    "name": "Masyn Winn",
    "team": "Cardinals",
    "opponent": "Jays",
    "metric": "r",
    "count": 8,
    "ab": 49,
    "date_range": "15",
    "count_per_ab": 0.163,
    "ab_per_game": 4.455,
    "expected_count_per_game": 0.727
  },
  {
    "date_est": "2025-06-11",
    "event_id": 401695925,
    "player_id": 4872691,
    "name": "Jackson Merrill",
    "team": "Padres",
    "opponent": "Dodgers",
    "metric": "r",
    "count": 8,
    "ab": 49,
    "date_range": "15",
    "count_per_ab": 0.163,
    "ab_per_game": 3.769,
    "expected_count_per_game": 0.615
  },
  {
    "date_est": "2025-06-11",
    "event_id": 401695927,
    "player_id": 41355,
    "name": "Geraldo Perdomo",
    "team": "D-Backs",
    "opponent": "Mariners",
    "metric": "r",
    "count": 8,
    "ab": 46,
    "date_range": "15",
    "count_per_ab": 0.174,
    "ab_per_game": 3.833,
    "expected_count_per_game": 0.667
  },
  {
    "date_est": "2025-06-11",
    "event_id": 401695916,
    "player_id": 39712,
    "name": "Oneil Cruz",
    "team": "Pirates",
    "opponent": "Marlins",
    "metric": "r",
    "count": 8,
    "ab": 44,
    "date_range": "15",
    "count_per_ab": 0.182,
    "ab_per_game": 4.0,
    "expected_count_per_game": 0.727
  },
  {
    "date_est": "2025-06-11",
    "event_id": 401695915,
    "player_id": 5080633,
    "name": "Jackson Holliday",
    "team": "Orioles",
    "opponent": "Tigers",
    "metric": "r",
    "count": 8,
    "ab": 39,
    "date_range": "15",
    "count_per_ab": 0.205,
    "ab_per_game": 3.9,
    "expected_count_per_game": 0.8
  },
  {
    "date_est": "2025-06-11",
    "event_id": 401695917,
    "player_id": 40754,
    "name": "Abraham Toro",
    "team": "Red Sox",
    "opponent": "Rays",
    "metric": "r",
    "count": 8,
    "ab": 37,
    "date_range": "15",
    "count_per_ab": 0.216,
    "ab_per_game": 3.7,
    "expected_count_per_game": 0.8
  },
  {
    "date_est": "2025-06-11",
    "event_id": 401695927,
    "player_id": 41215,
    "name": "Alek Thomas",
    "team": "D-Backs",
    "opponent": "Mariners",
    "metric": "r",
    "count": 8,
    "ab": 36,
    "date_range": "15",
    "count_per_ab": 0.222,
    "ab_per_game": 3.0,
    "expected_count_per_game": 0.667
  },
  {
    "date_est": "2025-06-11",
    "event_id": 401695921,
    "player_id": 4905884,
    "name": "Maikel Garcia",
    "team": "Royals",
    "opponent": "Yankees",
    "metric": "r",
    "count": 8,
    "ab": 34,
    "date_range": "15",
    "count_per_ab": 0.235,
    "ab_per_game": 3.778,
    "expected_count_per_game": 0.889
  },
  {
    "date_est": "2025-06-11",
    "event_id": 401695922,
    "player_id": 34230,
    "name": "Willi Castro",
    "team": "Twins",
    "opponent": "Rangers",
    "metric": "r",
    "count": 8,
    "ab": 34,
    "date_range": "15",
    "count_per_ab": 0.235,
    "ab_per_game": 3.4,
    "expected_count_per_game": 0.8
  },
  {
    "date_est": "2025-06-11",
    "event_id": 401695917,
    "player_id": 5012120,
    "name": "Carlos Narvaez",
    "team": "Red Sox",
    "opponent": "Rays",
    "metric": "r",
    "count": 8,
    "ab": 29,
    "date_range": "15",
    "count_per_ab": 0.276,
    "ab_per_game": 3.222,
    "expected_count_per_game": 0.889
  },
  {
    "date_est": "2025-06-11",
    "event_id": 401695918,
    "player_id": 30830,
    "name": "Starling Marte",
    "team": "Mets",
    "opponent": "Nationals",
    "metric": "r",
    "count": 8,
    "ab": 25,
    "date_range": "15",
    "count_per_ab": 0.32,
    "ab_per_game": 3.125,
    "expected_count_per_game": 1.0
  },
  {
    "date_est": "2025-06-11",
    "event_id": 401695914,
    "player_id": 32801,
    "name": "Jose Ramirez",
    "team": "Guardians",
    "opponent": "Reds",
    "metric": "r",
    "count": 7,
    "ab": 41,
    "date_range": "15",
    "count_per_ab": 0.171,
    "ab_per_game": 3.727,
    "expected_count_per_game": 0.636
  },
  {
    "date_est": "2025-06-11",
    "event_id": 401695923,
    "player_id": 32532,
    "name": "Willson Contreras",
    "team": "Cardinals",
    "opponent": "Jays",
    "metric": "r",
    "count": 7,
    "ab": 41,
    "date_range": "15",
    "count_per_ab": 0.171,
    "ab_per_game": 3.727,
    "expected_count_per_game": 0.636
  },
  {
    "date_est": "2025-06-11",
    "event_id": 401695920,
    "player_id": 4781491,
    "name": "Yainer Diaz",
    "team": "Astros",
    "opponent": "White Sox",
    "metric": "r",
    "count": 7,
    "ab": 39,
    "date_range": "15",
    "count_per_ab": 0.179,
    "ab_per_game": 3.545,
    "expected_count_per_game": 0.636
  },
  {
    "date_est": "2025-06-11",
    "event_id": 401695927,
    "player_id": 32512,
    "name": "Ketel Marte",
    "team": "D-Backs",
    "opponent": "Mariners",
    "metric": "r",
    "count": 7,
    "ab": 35,
    "date_range": "15",
    "count_per_ab": 0.2,
    "ab_per_game": 3.5,
    "expected_count_per_game": 0.7
  },
  {
    "date_est": "2025-06-11",
    "event_id": 401695926,
    "player_id": 40854,
    "name": "Jo Adell",
    "team": "Angels",
    "opponent": "A's",
    "metric": "r",
    "count": 7,
    "ab": 34,
    "date_range": "15",
    "count_per_ab": 0.206,
    "ab_per_game": 3.091,
    "expected_count_per_game": 0.636
  },
  {
    "date_est": "2025-06-11",
    "event_id": 401695913,
    "player_id": 33710,
    "name": "Trea Turner",
    "team": "Phillies",
    "opponent": "Cubs",
    "metric": "r",
    "count": 6,
    "ab": 50,
    "date_range": "15",
    "count_per_ab": 0.12,
    "ab_per_game": 4.167,
    "expected_count_per_game": 0.5
  },
  {
    "date_est": "2025-06-11",
    "event_id": 401695922,
    "player_id": 41205,
    "name": "Trevor Larnach",
    "team": "Twins",
    "opponent": "Rangers",
    "metric": "r",
    "count": 6,
    "ab": 48,
    "date_range": "15",
    "count_per_ab": 0.125,
    "ab_per_game": 4.364,
    "expected_count_per_game": 0.545
  },
  {
    "date_est": "2025-06-11",
    "event_id": 401695925,
    "player_id": 31606,
    "name": "Xander Bogaerts",
    "team": "Padres",
    "opponent": "Dodgers",
    "metric": "r",
    "count": 6,
    "ab": 44,
    "date_range": "15",
    "count_per_ab": 0.136,
    "ab_per_game": 3.667,
    "expected_count_per_game": 0.5
  },
  {
    "date_est": "2025-06-11",
    "event_id": 401695916,
    "player_id": 35020,
    "name": "Ke'Bryan Hayes",
    "team": "Pirates",
    "opponent": "Marlins",
    "metric": "r",
    "count": 6,
    "ab": 40,
    "date_range": "15",
    "count_per_ab": 0.15,
    "ab_per_game": 3.636,
    "expected_count_per_game": 0.545
  },
  {
    "date_est": "2025-06-11",
    "event_id": 401695917,
    "player_id": 32150,
    "name": "Trevor Story",
    "team": "Red Sox",
    "opponent": "Rays",
    "metric": "r",
    "count": 6,
    "ab": 38,
    "date_range": "15",
    "count_per_ab": 0.158,
    "ab_per_game": 3.8,
    "expected_count_per_game": 0.6
  },
  {
    "date_est": "2025-06-11",
    "event_id": 401695919,
    "player_id": 41179,
    "name": "Brice Turang",
    "team": "Brewers",
    "opponent": "Braves",
    "metric": "r",
    "count": 6,
    "ab": 34,
    "date_range": "15",
    "count_per_ab": 0.176,
    "ab_per_game": 3.4,
    "expected_count_per_game": 0.6
  },
  {
    "date_est": "2025-06-11",
    "event_id": 401695922,
    "player_id": 41587,
    "name": "Ryan Jeffers",
    "team": "Twins",
    "opponent": "Rangers",
    "metric": "r",
    "count": 6,
    "ab": 34,
    "date_range": "15",
    "count_per_ab": 0.176,
    "ab_per_game": 3.4,
    "expected_count_per_game": 0.6
  },
  {
    "date_est": "2025-06-11",
    "event_id": 401695919,
    "player_id": 42958,
    "name": "Joey Ortiz",
    "team": "Brewers",
    "opponent": "Braves",
    "metric": "r",
    "count": 6,
    "ab": 32,
    "date_range": "15",
    "count_per_ab": 0.188,
    "ab_per_game": 3.2,
    "expected_count_per_game": 0.6
  },
  {
    "date_est": "2025-06-11",
    "event_id": 401695917,
    "player_id": 4872648,
    "name": "Marcelo Mayer",
    "team": "Red Sox",
    "opponent": "Rays",
    "metric": "r",
    "count": 6,
    "ab": 25,
    "date_range": "15",
    "count_per_ab": 0.24,
    "ab_per_game": 2.5,
    "expected_count_per_game": 0.6
  },
  {
    "date_est": "2025-06-11",
    "event_id": 401695914,
    "player_id": 41183,
    "name": "Bo Naylor",
    "team": "Guardians",
    "opponent": "Reds",
    "metric": "r",
    "count": 6,
    "ab": 24,
    "date_range": "15",
    "count_per_ab": 0.25,
    "ab_per_game": 2.667,
    "expected_count_per_game": 0.667
  },
  {
    "date_est": "2025-06-11",
    "event_id": 401695926,
    "player_id": 4666100,
    "name": "Zach Neto",
    "team": "Angels",
    "opponent": "A's",
    "metric": "r",
    "count": 5,
    "ab": 47,
    "date_range": "15",
    "count_per_ab": 0.106,
    "ab_per_game": 4.273,
    "expected_count_per_game": 0.455
  },
  {
    "date_est": "2025-06-11",
    "event_id": 401695927,
    "player_id": 32367,
    "name": "Eugenio Suarez",
    "team": "D-Backs",
    "opponent": "Mariners",
    "metric": "r",
    "count": 5,
    "ab": 47,
    "date_range": "15",
    "count_per_ab": 0.106,
    "ab_per_game": 3.917,
    "expected_count_per_game": 0.417
  },
  {
    "date_est": "2025-06-11",
    "event_id": 401695913,
    "player_id": 33712,
    "name": "Kyle Schwarber",
    "team": "Phillies",
    "opponent": "Cubs",
    "metric": "r",
    "count": 5,
    "ab": 46,
    "date_range": "15",
    "count_per_ab": 0.109,
    "ab_per_game": 3.833,
    "expected_count_per_game": 0.417
  },
  {
    "date_est": "2025-06-11",
    "event_id": 401695926,
    "player_id": 4739755,
    "name": "Nolan Schanuel",
    "team": "Angels",
    "opponent": "A's",
    "metric": "r",
    "count": 5,
    "ab": 44,
    "date_range": "15",
    "count_per_ab": 0.114,
    "ab_per_game": 4.0,
    "expected_count_per_game": 0.455
  },
  {
    "date_est": "2025-06-11",
    "event_id": 401695917,
    "player_id": 41610,
    "name": "Jarren Duran",
    "team": "Red Sox",
    "opponent": "Rays",
    "metric": "r",
    "count": 5,
    "ab": 43,
    "date_range": "15",
    "count_per_ab": 0.116,
    "ab_per_game": 4.3,
    "expected_count_per_game": 0.5
  },
  {
    "date_est": "2025-06-11",
    "event_id": 401695923,
    "player_id": 41773,
    "name": "Brendan Donovan",
    "team": "Cardinals",
    "opponent": "Jays",
    "metric": "r",
    "count": 5,
    "ab": 43,
    "date_range": "15",
    "count_per_ab": 0.116,
    "ab_per_game": 3.909,
    "expected_count_per_game": 0.455
  },
  {
    "date_est": "2025-06-11",
    "event_id": 401695927,
    "player_id": 35066,
    "name": "Josh Naylor",
    "team": "D-Backs",
    "opponent": "Mariners",
    "metric": "r",
    "count": 5,
    "ab": 43,
    "date_range": "15",
    "count_per_ab": 0.116,
    "ab_per_game": 3.909,
    "expected_count_per_game": 0.455
  },
  {
    "date_est": "2025-06-11",
    "event_id": 401695920,
    "player_id": 31662,
    "name": "Jose Altuve",
    "team": "Astros",
    "opponent": "White Sox",
    "metric": "r",
    "count": 5,
    "ab": 42,
    "date_range": "15",
    "count_per_ab": 0.119,
    "ab_per_game": 3.818,
    "expected_count_per_game": 0.455
  },
  {
    "date_est": "2025-06-11",
    "event_id": 401695916,
    "player_id": 28701,
    "name": "Andrew McCutchen",
    "team": "Pirates",
    "opponent": "Marlins",
    "metric": "r",
    "count": 5,
    "ab": 40,
    "date_range": "15",
    "count_per_ab": 0.125,
    "ab_per_game": 4.0,
    "expected_count_per_game": 0.5
  },
  {
    "date_est": "2025-06-11",
    "event_id": 401695917,
    "player_id": 4987382,
    "name": "Ceddanne Rafaela",
    "team": "Red Sox",
    "opponent": "Rays",
    "metric": "r",
    "count": 5,
    "ab": 40,
    "date_range": "15",
    "count_per_ab": 0.125,
    "ab_per_game": 4.0,
    "expected_count_per_game": 0.5
  },
  {
    "date_est": "2025-06-11",
    "event_id": 401695921,
    "player_id": 41171,
    "name": "Jonathan India",
    "team": "Royals",
    "opponent": "Yankees",
    "metric": "r",
    "count": 5,
    "ab": 40,
    "date_range": "15",
    "count_per_ab": 0.125,
    "ab_per_game": 4.0,
    "expected_count_per_game": 0.5
  },
  {
    "date_est": "2025-06-11",
    "event_id": 401695923,
    "player_id": 4448736,
    "name": "Lars Nootbaar",
    "team": "Cardinals",
    "opponent": "Jays",
    "metric": "r",
    "count": 5,
    "ab": 40,
    "date_range": "15",
    "count_per_ab": 0.125,
    "ab_per_game": 4.0,
    "expected_count_per_game": 0.5
  },
  {
    "date_est": "2025-06-11",
    "event_id": 401695920,
    "player_id": 40719,
    "name": "Jake Meyers",
    "team": "Astros",
    "opponent": "White Sox",
    "metric": "r",
    "count": 5,
    "ab": 40,
    "date_range": "15",
    "count_per_ab": 0.125,
    "ab_per_game": 3.636,
    "expected_count_per_game": 0.455
  }
]